extexsion/APK解包工具.exe
extexsion/__init__.py
extexsion/icon.py
extexsion/icon.pyi
extexsion/main.py
extexsion/main.pyi
extexsion-0.2.1.dist-info/LICENSE.txt
extexsion-0.2.1.dist-info/METADATA
extexsion-0.2.1.dist-info/WHEEL
extexsion-0.2.1.dist-info/top_level.txt
extexsion-0.2.1.dist-info/RECORD
