Metadata-Version: 2.2
Name: extexsion
Version: 0.2.1
Summary: extexsion
Author: huang yi yi
Author-email: 363766687@qq.com
Requires-Python: >=3.6
License-File: LICENSE.txt
Requires-Dist: requests>=2.32.2.post1
Requires-Dist: pywin32
Requires-Dist: mutagen
Requires-Dist: wmi
Requires-Dist: beautifulsoup4
Requires-Dist: pyunpack
Requires-Dist: rarfile
Requires-Dist: py7zr
Dynamic: author
Dynamic: author-email
Dynamic: description
Dynamic: requires-dist
Dynamic: requires-python
Dynamic: summary
